TOOLS.MD
quickder.arpa2-1.4.0-py3.7-nspkg.pth
arpa2/__init__.py
arpa2/quickder_tools/__init__.py
arpa2/quickder_tools/asn1literate.py
arpa2/quickder_tools/asn2quickder.py
arpa2/quickder_tools/derdump.py
arpa2/quickder_tools/packstx.py
arpa2/quickder_tools/util.py
arpa2/quickder_tools/generators/__init__.py
arpa2/quickder_tools/generators/header.py
arpa2/quickder_tools/generators/python.py
arpa2/quickder_tools/generators/source.py
arpa2/quickder_tools/generators/testdata.py
img/derdump-screenshot.png
quickder/arpa2/RemotePKCS11.py
quickder/arpa2/__init__.py
quickder/arpa2/kxover.py
quickder/itu/__init__.py
quickder/rfc/__init__.py
quickder/rfc/rfc1422.py
quickder/rfc/rfc2315.py
quickder/rfc/rfc2578.py
quickder/rfc/rfc2898.py
quickder/rfc/rfc3062.py
quickder/rfc/rfc3280.py
quickder/rfc/rfc3909.py
quickder/rfc/rfc4120.py
quickder/rfc/rfc4178.py
quickder/rfc/rfc4373.py
quickder/rfc/rfc4511.py
quickder/rfc/rfc4531.py
quickder/rfc/rfc4556.py
quickder/rfc/rfc5208.py
quickder/rfc/rfc5280.py
quickder/rfc/rfc5805.py
quickder/rfc/rfc7292.py
quickder.arpa2-1.4.0.dist-info/LICENSE.MD
quickder.arpa2-1.4.0.dist-info/METADATA
quickder.arpa2-1.4.0.dist-info/WHEEL
quickder.arpa2-1.4.0.dist-info/namespace_packages.txt
quickder.arpa2-1.4.0.dist-info/top_level.txt
quickder.arpa2-1.4.0.dist-info/RECORD
