Metadata-Version: 2.1
Name: quickder.arpa2
Version: 1.4.0
Summary: Prebuilt Quick DER includes based on ASN.1 in RFCs
Home-page: https://gitlab.com/arpa2/quick-der
Author: Rick van Rein
Author-email: rick@openfortress.nl
License: BSD-2
Platform: UNKNOWN
Requires-Dist: arpa2.quickder
